hipsta/__init__.py
hipsta/computeCubeParam.py
hipsta/computeThickness.py
hipsta/createSurface.py
hipsta/createTetraLabels.py
hipsta/createTetraMesh.py
hipsta/cutTetra.py
hipsta/hipsta.py
hipsta/processImage.py
hipsta/processLabels.py
hipsta/processMask.py
hipsta/removeBoundaryMask.py
hipsta/cfg/__init__.py
hipsta/cfg/atlases.py
hipsta/cfg/config.py
hipsta/cfg/logging.py
hipsta/cfg/version.py
hipsta/cli/__init__.py
hipsta/doc/DOCUMENTATION.md
hipsta/doc/__init__.py
hipsta/doc/documentation.py
hipsta/utils/__init__.py
hipsta/utils/check_surface.py
hipsta/utils/create_supplementary_files.py
hipsta/utils/get_levelsets.py
hipsta/utils/map_values.py
hipsta/utils/qc_plots.py
hipsta-0.9.1.dist-info/LICENSE
hipsta-0.9.1.dist-info/METADATA
hipsta-0.9.1.dist-info/WHEEL
hipsta-0.9.1.dist-info/entry_points.txt
hipsta-0.9.1.dist-info/top_level.txt
hipsta-0.9.1.dist-info/RECORD
