Metadata-Version: 2.1
Name: hipsta
Version: 0.9.1
Summary: A python package for hippocampal shape and thickness analysis
Author-email: Kersten Diers <kersten.diers@dzne.de>, Martin Reuter <martin.reuter@dzne.de>
Maintainer-email: Kersten Diers <kersten.diers@dzne.de>, Martin Reuter <martin.reuter@dzne.de>
License: MIT License
Project-URL: homepage, https://github.com/Deep-MI/Hipsta
Project-URL: documentation, https://github.com/Deep-MI/Hipsta
Project-URL: source, https://github.com/Deep-MI/Hipsta
Project-URL: tracker, https://github.com/Deep-MI/Hipsta/issues
Keywords: hippocampus,shape,thickness,geometry
Classifier: Operating System :: Unix
Classifier: Operating System :: MacOS
Classifier: Programming Language :: Python :: 3 :: Only
Classifier: Programming Language :: Python :: 3.8
Classifier: Programming Language :: Python :: 3.9
Classifier: Programming Language :: Python :: 3.10
Classifier: Programming Language :: Python :: 3.11
Classifier: Natural Language :: English
Classifier: License :: OSI Approved :: MIT License
Classifier: Intended Audience :: Science/Research
Requires-Python: >=3.8
License-File: LICENSE
Requires-Dist: nibabel ==3.2.2
Requires-Dist: numpy >=1.22.3
Requires-Dist: pandas >=1.3.0
Requires-Dist: plotly ==5.6.0
Requires-Dist: pyacvd ==0.2.9
Requires-Dist: pyvista ==0.37.0
Requires-Dist: scipy >=1.8.0
Requires-Dist: nilearn ==0.8.1
Requires-Dist: lapy >=1.0.0
Requires-Dist: kaleido ==0.2.1
Requires-Dist: scikit-image
Requires-Dist: importlib-resources
Provides-Extra: all
Requires-Dist: hipsta[doc] ; extra == 'all'
Requires-Dist: hipsta[build] ; extra == 'all'
Requires-Dist: hipsta[style] ; extra == 'all'
Provides-Extra: build
Requires-Dist: build ; extra == 'build'
Requires-Dist: twine ; extra == 'build'
Provides-Extra: doc
Requires-Dist: furo !=2023.8.17 ; extra == 'doc'
Requires-Dist: matplotlib ; extra == 'doc'
Requires-Dist: memory-profiler ; extra == 'doc'
Requires-Dist: numpydoc ; extra == 'doc'
Requires-Dist: sphinx !=7.2.* ; extra == 'doc'
Requires-Dist: sphinxcontrib-bibtex ; extra == 'doc'
Requires-Dist: sphinx-copybutton ; extra == 'doc'
Requires-Dist: sphinx-design ; extra == 'doc'
Requires-Dist: sphinx-gallery ; extra == 'doc'
Requires-Dist: sphinx-issues ; extra == 'doc'
Requires-Dist: myst-parser ; extra == 'doc'
Requires-Dist: pypandoc ; extra == 'doc'
Requires-Dist: nbsphinx ; extra == 'doc'
Requires-Dist: IPython ; extra == 'doc'
Requires-Dist: ipykernel ; extra == 'doc'
Provides-Extra: full
Requires-Dist: hipsta[all] ; extra == 'full'
Provides-Extra: style
Requires-Dist: bibclean ; extra == 'style'
Requires-Dist: black ; extra == 'style'
Requires-Dist: codespell ; extra == 'style'
Requires-Dist: isort ; extra == 'style'
Requires-Dist: pydocstyle[toml] ; extra == 'style'
Requires-Dist: ruff ; extra == 'style'
Provides-Extra: test
Requires-Dist: pytest ; extra == 'test'
Requires-Dist: pytest-cov ; extra == 'test'
Requires-Dist: pytest-timeout ; extra == 'test'
